{
  "params": [
    {
      "parameter": "roomSize",
      "value": {
        "type": "vectorRange",
        "minX": 15,
        "minY": 0,
        "minZ": 15,
        "maxX": 35,
        "maxY": 0,
        "maxZ": 35
      },
      "locked": false
    },
    {
      "parameter": "corridorSize",
      "value": {
        "type": "vector",
        "x": 3,
        "y": 0,
        "z": 3
      },
      "locked": false
    },
    {
      "parameter": "enemySpawnRate",
      "value": { "type": "number", "value": 50 },
      "locked": false
    },
    {
      "parameter": "itemsPerRoom",
      "value": {
        "type": "range",
        "min": 0,
        "max": 3
      }
    },
    {
      "parameter": "enemiesPerRoom",
      "value": {
        "type": "range",
        "min": 0,
        "max": 3
      }
    },
    {
      "parameter": "roomCount",
      "value": { "type": "number", "value": 10 },
      "locked": true
    }
  ],
  "baseDungeon": [
    {
      "type": "start"
    },
    {
      "type": "explore"
    },
    {
      "type": "end"
    }
  ],
  "dungeonPatterns": [
    {
      "matches": [
        {
          "type": "explore"
        }
      ],
      "replacer": [
        {
          "type": "explore"
        },
        {
          "type": "combat"
        },
        {
          "type": "item"
        }
      ]
    }
  ]
}
